{
  "project_info": {
    "project_number": "44584806569",
    "project_id": "personalised-app-abaad",
    "storage_bucket": "personalised-app-abaad.appspot.com"
  },
  "client": [
    {
      "client_info": {
        "mobilesdk_app_id": "1:44584806569:android:a63d82300a7d2f425be1b8",
        "android_client_info": {
          "package_name": "com.example.todo"
        }
      },
      "oauth_client": [],
      "api_key": [
        {
          "current_key": "AIzaSyDC8QI0i-i7GbETPGD-UF20M1f3DLzCNdE"
        }
      ],
      "services": {
        "appinvite_service": {
          "other_platform_oauth_client": []
        }
      }
    }
  ],
  "configuration_version": "1"
}